Kani_STT/__init__.py
kani_stt-0.1.dist-info/METADATA
kani_stt-0.1.dist-info/WHEEL
kani_stt-0.1.dist-info/top_level.txt
kani_stt-0.1.dist-info/RECORD
